mutanno/__init__.py
mutanno/_logging.py
mutanno/_options.py
mutanno/_version.py
mutanno/annotvcf.py
mutanno/convert.py
mutanno/external_functions.py
mutanno/makedata.py
mutanno/makegenedata.py
mutanno/precal.py
mutanno/preprocess__.py
mutanno/renderer.py
mutanno/validate.py
mutanno/viewer.py
mutanno/data/CLINVAR_hg38_20200329_submission.sorted.tsi.gz_idmap.txt.gz
mutanno/data/__init__.py
mutanno/data/conf.json
mutanno/data/sourcelist.json
mutanno/download/__init__.py
mutanno/download/download.py
mutanno/model/__init__.py
mutanno/model/datasource.py
mutanno/model/datastructure.py
mutanno/preprocess/__init__.py
mutanno/preprocess/preproc_clinvar.py
mutanno/preprocess/preproc_gnomad.py
mutanno/preprocess/preproc_spliceai.py
mutanno/preprocess/preproc_vep.py
mutanno/reader/__init__.py
mutanno/reader/tsireader.py
mutanno/util/__init__.py
mutanno/util/file_util.py
mutanno/util/proc_util.py
mutanno/util/region_util.py
mutanno/util/seq_util.py
mutanno/util/struct_util.py
mutanno/util/vcf_util.py
mutanno/util/vep_util.py
mutanno/web/__init__.py
mutanno/web/admin.py
mutanno/web/apps.py
mutanno/web/asgi.py
mutanno/web/conf.py
mutanno/web/gene.py
mutanno/web/models.py
mutanno/web/settings.py
mutanno/web/stat.py
mutanno/web/tests.py
mutanno/web/urls.py
mutanno/web/variant.py
mutanno/web/views.py
mutanno/web/wsgi.py
mutanno/web/migrations/__init__.py
mutanno/web/static/__init__.py
mutanno/web/static/css/__init__.py
mutanno/web/static/css/bootstrap-select.min.css
mutanno/web/static/css/bootstrap-theme.min.css
mutanno/web/static/css/bootstrap.css
mutanno/web/static/css/bootstrap.min.css
mutanno/web/static/css/drop-theme-basic.css
mutanno/web/static/css/gene-style.css
mutanno/web/static/css/igv-all.css
mutanno/web/static/css/jquery-ui-1.12.1.min.css
mutanno/web/static/css/jquery.treegrid.css
mutanno/web/static/css/lbl_tooltip.css
mutanno/web/static/css/main.css
mutanno/web/static/css/matrixviewer.css
mutanno/web/static/css/table-style.css
mutanno/web/static/css/table-stype.css
mutanno-0.4.8.dist-info/LICENSE
mutanno-0.4.8.dist-info/METADATA
mutanno-0.4.8.dist-info/WHEEL
mutanno-0.4.8.dist-info/entry_points.txt
mutanno-0.4.8.dist-info/top_level.txt
mutanno-0.4.8.dist-info/RECORD
